{"id":100044,"info":{"name":"corazon de melon Sona LOL","description":"tema crado por Sora.Kagamine02","format":"uso","category":"corazondemelon","updatedAt":"2014-04-06T17:26:48.000Z","license":"NO-REDISTRIBUTION","author":{"id":262134,"name":"saikanokagamine"}},"stats":{"installs":{"total":774,"weekly":0}},"screenshots":{"main":"100044_after.gif","isMainArchived":false},"discussions":{"stats":{"discussionsCount":0,"commentsCount":0}},"style":{"css":"@-moz-document domain(\"corazondemelon.es\"), domain(\"corazondemelon.es\") {\r\n#container{\r\nbackground-image : url(http://fc09.deviantart.net/fs70/f/2014/074/2/d/fondo_by_saikanokagamine-d7acxit.png) !important ;\r\n}\r\n#container.connected #header { background-image : url(http://fc07.deviantart.net/fs71/f/2014/074/a/f/base_by_saikanokagamine-d7acyl5.png) !important ;\r\n}\r\n.idcard-member { background : url(http://fc03.deviantart.net/fs70/f/2014/074/7/4/tarjeta_by_saikanokagamine-d7acxg7.png) no-repeat !important ;\r\n}\r\n}"}}