{
  "id": 100821,
  "info": {
    "name": "Smashboards Adblock",
    "description": "Blocks advertisements and their placeholders on Smashboards.",
    "additionalInfo": null,
    "format": "uso",
    "category": "smashboards",
    "createdAt": "2014-04-25T14:06:30Z",
    "updatedAt": "2014-04-25T14:06:30Z",
    "license": "NONE",
    "author": {
      "id": 152848,
      "name": "nateify",
      "homepage": "http://natecohen.me/",
      "paypalEmail": null
    }
  },
  "stats": {
    "installs": {
      "total": 178,
      "weekly": 0
    },
    "rating": null
  },
  "screenshots": {
    "main": {
      "name": "100821-0.webp",
      "archived": true
    },
    "additional": null
  },
  "obsolete": null,
  "style": {
    "css": "@namespace url(http://www.w3.org/1999/xhtml);\r\n\r\n@-moz-document domain(\"smashboards.com\") {\r\n#noticeMain,.sidebar div[align=\"center\"]:first-of-type, .sidebar div[align=\"center\"]:last-of-type,.pageContent div[style=\"position: relative; height: 90px; margin-bottom: 10px;\"]:last-of-type{display:none!important}\r\n}",
    "settings": []
  },
  "deleteReason": null
}