{
  "id": 12161,
  "info": {
    "name": "FreeCulture.org Vista fonts",
    "description": "Bog standard ClearType font replacement. Particularly good on those otherwise horribly jaggy header links.",
    "additionalInfo": null,
    "format": "uso",
    "category": "freeculture",
    "createdAt": "2008-11-17T17:36:54Z",
    "updatedAt": "2008-11-17T17:36:54Z",
    "license": "NONE",
    "author": {
      "id": 16818,
      "name": "Artfunkel",
      "homepage": null,
      "paypalEmail": null
    }
  },
  "stats": {
    "installs": {
      "total": 166,
      "weekly": 0
    },
    "rating": null
  },
  "screenshots": {
    "main": {
      "name": "12161-0.webp",
      "archived": true
    },
    "additional": null
  },
  "obsolete": null,
  "style": {
    "css": "@namespace url(http://www.w3.org/1999/xhtml);\r\n\r\n@-moz-document domain(\"freeculture.org\") {\r\n\r\n#menu-ul { font-family:consolas, courier new, courier, monospace !important; }\r\n\r\nbody { font-size-adjust:0.5 !important; font-family:Calibri !important ; }\r\n\r\nh1,h2,h3,h4 { font-family:Cambria !important; font-weight:bold !important; }\r\n\r\n}",
    "settings": []
  },
  "deleteReason": null
}