{
  "id": 150583,
  "info": {
    "name": "aws-navbar-color-by-region",
    "description": "Colorize AWS Management Console navigation bar by region.",
    "additionalInfo": null,
    "format": "uso",
    "category": "amazon",
    "createdAt": "2017-11-03T03:34:37.000Z",
    "updatedAt": "2020-09-24T11:34:41.000Z",
    "license": "NO-REDISTRIBUTION",
    "author": {
      "id": 538954,
      "name": "小原一哉"
    }
  },
  "stats": {
    "installs": {
      "total": 194,
      "weekly": 0
    }
  },
  "screenshots": {
    "main": {
      "name": "150583_after.png",
      "archived": true
    },
    "additional": [
      {
        "name": "150583_additional_28464.png",
        "archived": true
      },
      {
        "name": "150583_additional_28465.png",
        "archived": true
      }
    ]
  },
  "discussions": {
    "stats": {
      "discussionsCount": 0,
      "commentsCount": 0
    },
    "data": []
  },
  "style": {
    "css": "@-moz-document domain(af-south-1.console.aws.amazon.com) { [data-testid=\"awsc-nav-header-viewport-shelf-inner\"] { background-color: hsl(157, 50%, 30%); } }\r\n@-moz-document domain(ap-east-1.console.aws.amazon.com) { [data-testid=\"awsc-nav-header-viewport-shelf-inner\"] { background-color: hsl(315, 50%, 30%); } }\r\n@-moz-document domain(ap-northeast-1.console.aws.amazon.com) { [data-testid=\"awsc-nav-header-viewport-shelf-inner\"] { background-color: hsl(164, 50%, 30%); } }\r\n@-moz-document domain(ap-northeast-2.console.aws.amazon.com) { [data-testid=\"awsc-nav-header-viewport-shelf-inner\"] { background-color: hsl(99, 50%, 30%); } }\r\n@-moz-document domain(ap-south-1.console.aws.amazon.com) { [data-testid=\"awsc-nav-header-viewport-shelf-inner\"] { background-color: hsl(348, 50%, 30%); } }\r\n@-moz-document domain(ap-southeast-1.console.aws.amazon.com) { [data-testid=\"awsc-nav-header-viewport-shelf-inner\"] { background-color: hsl(93, 50%, 30%); } }\r\n@-moz-document domain(ap-southeast-2.console.aws.amazon.com) { [data-testid=\"awsc-nav-header-viewport-shelf-inner\"] { background-color: hsl(101, 50%, 30%); } }\r\n@-moz-document domain(ca-central-1.console.aws.amazon.com) { [data-testid=\"awsc-nav-header-viewport-shelf-inner\"] { background-color: hsl(290, 50%, 30%); } }\r\n@-moz-document domain(eu-central-1.console.aws.amazon.com) { [data-testid=\"awsc-nav-header-viewport-shelf-inner\"] { background-color: hsl(349, 50%, 30%); } }\r\n@-moz-document domain(eu-north-1.console.aws.amazon.com) { [data-testid=\"awsc-nav-header-viewport-shelf-inner\"] { background-color: hsl(111, 50%, 30%); } }\r\n@-moz-document domain(eu-south-1.console.aws.amazon.com) { [data-testid=\"awsc-nav-header-viewport-shelf-inner\"] { background-color: hsl(114, 50%, 30%); } }\r\n@-moz-document domain(eu-west-1.console.aws.amazon.com) { [data-testid=\"awsc-nav-header-viewport-shelf-inner\"] { background-color: hsl(252, 50%, 30%); } }\r\n@-moz-document domain(eu-west-2.console.aws.amazon.com) { [data-testid=\"awsc-nav-header-viewport-shelf-inner\"] { background-color: hsl(305, 50%, 30%); } }\r\n@-moz-document domain(eu-west-3.console.aws.amazon.com) { [data-testid=\"awsc-nav-header-viewport-shelf-inner\"] { background-color: hsl(56, 50%, 30%); } }\r\n@-moz-document domain(me-south-1.console.aws.amazon.com) { [data-testid=\"awsc-nav-header-viewport-shelf-inner\"] { background-color: hsl(17, 50%, 30%); } }\r\n@-moz-document domain(sa-east-1.console.aws.amazon.com) { [data-testid=\"awsc-nav-header-viewport-shelf-inner\"] { background-color: hsl(270, 50%, 30%); } }\r\n@-moz-document domain(us-east-1.console.aws.amazon.com) { [data-testid=\"awsc-nav-header-viewport-shelf-inner\"] { background-color: hsl(188, 50%, 30%); } }\r\n@-moz-document domain(us-east-2.console.aws.amazon.com) { [data-testid=\"awsc-nav-header-viewport-shelf-inner\"] { background-color: hsl(352, 50%, 30%); } }\r\n@-moz-document domain(us-west-1.console.aws.amazon.com) { [data-testid=\"awsc-nav-header-viewport-shelf-inner\"] { background-color: hsl(27, 50%, 30%); } }\r\n@-moz-document domain(us-west-2.console.aws.amazon.com) { [data-testid=\"awsc-nav-header-viewport-shelf-inner\"] { background-color: hsl(177, 50%, 30%); } }\r\n"
  }
}