{"id":169921,"info":{"name":"Pastel Purple Avatar Background - ROBLOX","description":"It's just a purple background - I made it for my acc. but take it if you want I guess.","format":"uso","category":"roblox","updatedAt":"2019-03-15T19:25:30.000Z","license":"NO-REDISTRIBUTION","author":{"id":786389,"name":"joifull"}},"stats":{"installs":{"total":6736,"weekly":63}},"screenshots":{"main":"169921_after.png","isMainArchived":false},"discussions":{"stats":{"discussionsCount":4,"commentsCount":1}},"style":{"css":"@-moz-document domain(\"roblox.com\")\r\n{\r\n  .avatar-back\r\n  {\r\n    background-image: url(https://cdn.discordapp.com/attachments/509904575227101185/556195509102968833/owo.png);\r\n  }\r\n}"}}