{
  "id": 58596,
  "info": {
    "name": "Karkat as the return to top arrow",
    "description": "thingy from your dash",
    "additionalInfo": "http://kizagui.deviantart.com/art/Karkat-252399706 this was the image used",
    "format": "uso",
    "category": "tumblr",
    "createdAt": "2011-12-29T00:54:18.000Z",
    "updatedAt": "2011-12-29T00:55:19.000Z",
    "license": "NO-REDISTRIBUTION",
    "author": {
      "id": 114459,
      "name": "==>"
    }
  },
  "stats": {
    "installs": {
      "total": 398,
      "weekly": 0
    }
  },
  "screenshots": {
    "main": {
      "name": "58596_after.jpeg",
      "archived": false
    }
  },
  "discussions": {
    "stats": {
      "discussionsCount": 0,
      "commentsCount": 0
    },
    "data": []
  },
  "style": {
    "css": "@namespace url(http://www.w3.org/1999/xhtml);\r\n\r\n\r\n\r\n@-moz-document url-prefix('http://www.tumblr.com/'), url-prefix('https://www.tumblr.com/')   {\r\n\r\n\r\n\r\n#return_to_top .return_to_top_icon{\r\n\r\nbackground: url('http://media.tumblr.com/tumblr_lwyjfrBQl51qbkyfi.png') no-repeat transparent!important}\r\n\r\n\r\n}\r\n\r\n\r\n"
  }
}