{
  "id": 88272,
  "info": {
    "name": "3dnews.ru without ads",
    "description": "Just make site easier and removes adverts",
    "additionalInfo": null,
    "format": "uso",
    "category": "3dnews",
    "createdAt": "2013-05-29T10:39:57Z",
    "updatedAt": "2013-07-02T06:13:11Z",
    "license": "CC0-1.0",
    "author": {
      "id": 190903,
      "name": "shekidem",
      "homepage": null,
      "paypalEmail": null
    }
  },
  "stats": {
    "installs": {
      "total": 207,
      "weekly": 0
    },
    "rating": null
  },
  "screenshots": {
    "main": {
      "name": "88272-0.webp",
      "archived": true
    },
    "additional": null
  },
  "obsolete": null,
  "style": {
    "css": "@namespace url(http://www.w3.org/1999/xhtml);\r\n\r\n@-moz-document domain(\"www.3dnews.ru\") {\r\n\r\n#right-sidebar,\r\n#left-sidebar,\r\n.ad-zone,\r\n#earAds,\r\n.footer-sub,\r\n.content-ads\r\n    {display: none !important;}\r\n\r\n#heading\r\n    {width: 1000px !important}\r\n\r\nhtml,\r\nbody,\r\n#wrapper,\r\n#global-wrapper\r\n    {width: 1000px !important;\r\n    padding: 0px !important;\r\n    position: relative !important;\r\n    margin: auto !important;}\r\n\r\n}",
    "settings": []
  },
  "deleteReason": null
}