{"id":103484,"name":"Hide JVC","category":"site","raw_subcategory":"facebook","subcategory":"facebook","style_tags":[],"description":"Cache les prénoms et retires les photos de profil.\r\n\r\nUtile pour les spiderman, et les fakes. :noel:","user":{"id":269338,"name":"GuklamJVC","email":"redacted","paypal_email":null,"homepage":null,"about":null,"license":null},"admin_delete_reason_id":null,"updated":"2014-07-17T11:20:39.000Z","weekly_install_count":0,"total_install_count":58,"rating":null,"screenshot_url":"https://userstyles.org/style_screenshots/103484_after.png?r=1588752331","url":"/styles/103484/hide-jvc","discussionsCount":0,"commentsCount":0,"css":"@-moz-document domain(www.facebook.com) {\r\n  \r\n._36 a{\r\n      background: black !important;\r\n      color: black !important;\r\n}\r\n\r\n._8o, ._8o .img, ._5ys_ img {\r\n  display: none !important;\r\n}\r\n    \r\n}"}