{
  "id": 113927,
  "name": "Younow - Dark",
  "description": "Just made it dark real quick. nothing special",
  "user": {
    "id": 290980,
    "name": "jetbl4ck",
    "email": "redacted",
    "paypal_email": null,
    "homepage": null,
    "about": null,
    "license": "publicdomain"
  },
  "updated": "2015-05-14T22:52:42.000Z",
  "weekly_install_count": 0,
  "total_install_count": 1072,
  "rating": null,
  "after_screenshot_name": "https://userstyles.org/style_screenshots/113927_after.jpeg?r=1596873970",
  "obsoleting_style_id": null,
  "obsoleting_style_name": null,
  "obsolete": 0,
  "admin_delete_reason_id": null,
  "obsoletion_message": null,
  "screenshots": null,
  "license": null,
  "created": "2015-05-14T22:52:42.000Z",
  "category": "site",
  "raw_subcategory": "younow",
  "subcategory": "younow",
  "additional_info": null,
  "style_tags": [],
  "css": "@-moz-document domain(\"www.younow.com\") {\r\nbody{\r\n\tbackground: #333333;\r\n}\r\n\r\n#player-toolbar,\r\n.navbar-content .search-box .search-field,\r\n.navbar-content .notifications .search-field,\r\n#playerheader,\r\n#sidebar-container,\r\n#sidebar-container #chatcomments\r\n{\r\n\tbackground-color: #444;\r\n}\r\n\r\nbody,\r\n#sidebar-container #chatcomments .chat-name, \r\n#sidebar-container #chatcomments .ynicon-level,\r\n#playerheader .broadcaster-name, \r\n#playerheader .broadcaster-name span, \r\n#playerheader .broadcaster-tags, \r\n#playerheader .broadcaster-setup-description,\r\n.player-toolbar-left .ynicon,\r\n#player-toolbar-right span,\r\n#player-toolbar-right .volume-icon,\r\n.toolbar-like-count, \r\n.share-like-count,\r\n#sidebar-container #topfan-slider\r\n{\r\n\tcolor: #568B08;\r\n}\r\n\r\n#sidebar-container #chatcomments span,\r\n#leftsidebar .trending-tag, \r\n#leftsidebar .trending-user, \r\n#leftsidebar .viewerCount,\r\n#playerheader .broadcaster-description,\r\n#leftsidebar .trending-tag, \r\n#leftsidebar .trending-user, \r\n#leftsidebar .viewerCount,\r\nspan,\r\n.navbar-content .explore-text a, \r\n.navbar-content .login-text a,\r\n.navbar-content .search-box .search-field, \r\n.navbar-content .notifications .search-field,\r\n#sidebar-container #chatcomments span\r\n{\r\n\tcolor: #FFF;\r\n}\r\n}",
  "discussions": [
    {
      "id": 48429,
      "name": "Reup",
      "rating": 3,
      "created": "2016-01-16T01:42:16.000Z",
      "author_name": "WinRar.",
      "author_id": 309273
    }
  ],
  "discussionsCount": 1,
  "commentsCount": 1,
  "userjs_url": "/styles/userjs/113927/younow-dark.user.js",
  "style_settings": []
}