{
  "id": 116624,
  "name": "Netflix 2016 Trimmed",
  "description": "A very simple style to eliminate the giant billboard.",
  "user": {
    "id": 192880,
    "name": "DarkanX",
    "email": "redacted",
    "paypal_email": "darkanx@gmail.com",
    "homepage": null,
    "about": null,
    "license": "publicdomain"
  },
  "updated": "2016-03-21T01:34:43.000Z",
  "weekly_install_count": 3,
  "total_install_count": 4760,
  "rating": null,
  "after_screenshot_name": "https://userstyles.org/style_screenshots/116624_after.jpeg?r=1602057913",
  "obsoleting_style_id": null,
  "obsoleting_style_name": null,
  "obsolete": 0,
  "admin_delete_reason_id": null,
  "obsoletion_message": null,
  "screenshots": null,
  "license": null,
  "created": "2015-07-19T11:37:52.000Z",
  "category": "site",
  "raw_subcategory": "netflix",
  "subcategory": "netflix",
  "additional_info": null,
  "style_tags": [],
  "css": "@-moz-document domain(\"netflix.com\"){\r\n\r\n.billboard-row { \r\n    display: none !important; }\r\n\r\n.hdSpace {\r\n    height: 120px !important; }\r\n\r\n}\r\n\r\n/*[[kids]]*/",
  "discussions": [
    {
      "id": 49213,
      "name": "Netfkix Kids page",
      "rating": 0,
      "created": "2016-03-19T13:47:09.000Z",
      "author_name": "Lateralus138",
      "author_id": 297443
    },
    {
      "id": 49214,
      "name": "Netflix Kids",
      "rating": 2,
      "created": "2016-03-19T13:50:00.000Z",
      "author_name": "Lateralus138",
      "author_id": 297443
    },
    {
      "id": 56698,
      "name": "Works Well!",
      "rating": 3,
      "created": "2017-06-19T23:38:10.000Z",
      "author_name": "Mboxer511",
      "author_id": 447255
    }
  ],
  "discussionsCount": 3,
  "commentsCount": 1,
  "userjs_url": "/styles/userjs/116624/netflix-2016-trimmed.user.js",
  "style_settings": [
    {
      "id": 450477,
      "style_id": 116624,
      "install_key": "kids",
      "label": "Remove Kid's Billboard",
      "ordinal": 0,
      "setting_type": "dropdown",
      "style_setting_options": [
        {
          "id": 1624451,
          "style_setting_id": 450477,
          "label": "Yes",
          "value": "@-moz-document url(\"https://www.netflix.com/Kids\"), url(\"https://www.netflix.com/kids\"){\r\n\r\n.mrows >:nth-child(1){\r\n    display: none !important;}\r\n\r\n}",
          "default": true,
          "ordinal": 1,
          "install_key": "kidsyes"
        },
        {
          "id": 1624450,
          "style_setting_id": 450477,
          "label": "No",
          "value": " ",
          "default": false,
          "ordinal": 2,
          "install_key": "kidsno"
        }
      ]
    }
  ]
}