{"id":119463,"name":"Amor Doce Tema: Kirito and Asuna","category":"site","raw_subcategory":"amordoce","subcategory":"amordoce","style_tags":[],"description":"Um lindo tema de Kirito e Asuna do famoso Sword Art Online","user":{"id":300457,"name":"Yukki Asuna","email":"redacted","paypal_email":null,"homepage":null,"about":null,"license":null},"admin_delete_reason_id":null,"updated":"2015-10-06T13:53:19.000Z","weekly_install_count":0,"total_install_count":43,"rating":null,"screenshot_url":"https://userstyles.org/style_screenshots/119463_after.png?r=1487505956","url":"/styles/119463/amor-doce-tema-kirito-and-asuna","discussionsCount":0,"commentsCount":0,"css":"@-moz-document domain(\"amordoce.com\") {\r\n#container{\r\nbackground-image : url(http://i58.tinypic.com/mbqses.jpg) !important ;\r\n}\r\n#container.connected #header { background-image : url(http://i59.tinypic.com/2luwehd.png) !important ;\r\n}\r\n.idcard-member { background : url(http://i59.tinypic.com/2prs13t.png)no-repeat !important ;\r\n}\r\n}\r\n\r\n@-moz-document regexp(\"http://www.amordoce.com/profil/hiyorihina\") {\r\n.idcard-member { background : url(http://i62.tinypic.com/11qu2vd.png) no-repeat !important ;\r\n}\r\n}"}