{"id":125775,"name":"Remove All Padding From Firefox Toolbar","category":"app","raw_subcategory":"browser","subcategory":"browser","style_tags":[],"description":"Remove All Padding From Firefox Toolbar","user":{"id":278913,"name":"Mikhoul","email":"redacted","paypal_email":null,"homepage":null,"about":null,"license":"publicdomain"},"admin_delete_reason_id":null,"updated":"2016-03-20T02:34:57.000Z","weekly_install_count":0,"total_install_count":129,"rating":null,"screenshot_url":"https://userstyles.org/style_screenshots/125775_after.png?r=1562486474","url":"/styles/125775/remove-all-padding-from-firefox-toolbar","discussionsCount":0,"commentsCount":0,"css":"@namespace url(\"http://www.mozilla.org/keymaster/gatekeeper/there.is.only.xul\"); \r\n\r\n /* Remove extra padding from the Navigation Bar and other toolbars*/\r\n  .toolbarbutton-icon\r\n{\r\n  -moz-appearance: none !important;\r\n  margin: 0px !important;\r\n  padding-right: 0px !important;\r\n  padding-left: 0px !important; \r\n  \r\n  padding-top: 0px !important;\r\n  padding-bottom: 0px !important;\r\n\r\n  margin-left: 0px !important; \r\n  margin-right: 0px !important;\r\n   \r\n}\r\n\r\n\r\n /* Set max toolbar height \r\n\r\ntoolbar {\r\n   max-height: 40px !important;\r\n  \r\n}   \r\n\r\ntoolbarbutton {max-height: 45px !important;\r\n  \r\n  }\r\n\r\n\r\n*/\r\n\r\n"}