{"id":141323,"name":"Dark Alchemy Mindworks","category":"site","raw_subcategory":"mindworkshop","subcategory":"mindworkshop","style_tags":[],"description":"A dark theme for Alchemy Mindworks' website.","user":{"id":410662,"name":"Xane Myers (X-Man)","email":"redacted","paypal_email":null,"homepage":"https://sites.google.com/view/xanem1","about":null,"license":"ccby"},"admin_delete_reason_id":null,"updated":"2017-04-14T15:59:21.000Z","weekly_install_count":0,"total_install_count":21,"rating":null,"screenshot_url":"https://userstyles.org/style_screenshots/141323_after.jpeg?r=1533470732","url":"/styles/141323/dark-alchemy-mindworks","discussionsCount":0,"commentsCount":0,"css":"@-moz-document domain(\"www.mindworkshop.info\") {\r\nbody\r\n{\r\nbackground-color: #444;\r\ncolor: #eee;\r\n}\r\n\r\nh1, h1 a, h2, h2 a, h3, h4, h5, h6\r\n{\r\n\tcolor: #acd;\r\n}\r\n\r\n#sidebar ul h2\r\n{\r\n\tcolor: #90b0c0;\r\n    text-shadow: 1px 1px 2px rgba(0,0,0,0.5);\r\n}\r\n\r\n.postmetadata\r\n{\r\n\tcolor: #b0b0b0;\r\n}\r\n\r\nimg\r\n{\r\n\tfilter: drop-shadow(0 0 10px white);\r\n}\r\n\r\na, a:visited, a:hover, a:focus\r\n{\r\ncolor: #bde;\r\n}\r\n\r\n#content\r\n{\r\nbackground-color: rgba(255,255,255,0.25);\r\nborder-right: 230px solid rgba(255,255,255,0.13);\r\n}\r\n\r\ncode\r\n{\r\nbackground-color: rgba(192,224,255,0.25);\r\ncolor: white;\r\nfont-size: 12pt;\r\n}\r\n\r\n#sidebar\r\n{\r\nbackground: none transparent !important;\r\n}\r\n}"}