{"id":141965,"name":"Overcast Dark Mode (overcast.fm)","category":"site","raw_subcategory":"overcast","subcategory":"overcast","style_tags":[],"description":"Dark mode for the Overcast podcast player website.","user":{"id":421022,"name":"Brendon Reyell","email":"redacted","paypal_email":null,"homepage":null,"about":null,"license":"publicdomain"},"admin_delete_reason_id":null,"updated":"2019-01-11T23:00:04.000Z","weekly_install_count":1,"total_install_count":51,"rating":null,"screenshot_url":"https://userstyles.org/style_screenshots/141965_after.png?r=1597133180","url":"/styles/141965/overcast-dark-mode-overcast-fm","discussionsCount":0,"commentsCount":0,"css":"@-moz-document domain(overcast.fm) {\r\n\r\nbody {\r\n\tbackground-color: #222;\r\n}\r\n\r\n.nav {\r\n\tborder-bottom-color: #aaa;\r\n}\r\n\r\n.ocseparatorbar {\r\n\tcolor: #fff;\r\n}\r\n\r\n.title {\r\n\tcolor: #fff;\r\n}\r\n\r\n.caption2 {\r\n\tcolor: #aaa;\r\n}\r\n\r\n.art {\r\n\tborder-color: #222;\r\n}\r\n\r\n.content {\r\n\tcolor: #fff;\r\n}\r\n\r\n#progresssliderbackground {\r\n\tborder-color: #aaa;\r\n}\r\n\r\n#speedcontrolcontainer {\r\n\tcolor: #222;\r\n}\r\n\r\n.speedlabel {\r\n\tmargin-top: 1px;\r\n}\r\n\r\n.feedcell:hover,\r\n.episodecell:hover,\r\n.extendedepisodecell:hover {\r\n\tbackground-color: rgba(252, 126, 15, 0.1);\r\n}\r\n\r\n.adrates {\r\n\tcolor: #000;\r\n}\r\n\r\ncode {\r\n\tbackground-color: #777;\r\n}\r\n}"}