{"id":149947,"name":"Black Slickdeals Redesign","category":"site","raw_subcategory":"slickdeals","subcategory":"slickdeals","style_tags":[],"description":"This is a black theme for Slickdeals. The current design only affects the pages when you aren't logged in.\r\n\r\nLogging in loads the classic view for the site which will be added later.","user":{"id":300878,"name":"kpr9","email":"redacted","paypal_email":null,"homepage":null,"about":null,"license":"publicdomain"},"admin_delete_reason_id":null,"updated":"2018-07-16T10:37:22.000Z","weekly_install_count":0,"total_install_count":146,"rating":null,"screenshot_url":"https://userstyles.org/style_screenshots/149947_after.jpeg?r=1592726870","url":"/styles/149947/black-slickdeals-redesign","discussionsCount":0,"commentsCount":0,"css":"@-moz-document url-prefix(\"https://slickdeals.net/deals/\"), domain(\"slickdeals.net\") {\r\nbody {\r\n    background-color: black;\r\n}\r\n\r\n/******** Homepage ********/\r\n\r\n/* search box */\r\ninput.searchBox {\r\n    color: lightgrey !important;\r\n    background-color: black;\r\n}\r\n.globalSearch {\r\n    background-color: black;\r\n}\r\n\r\n/* login button */\r\n.button {\r\n    color: white !important;\r\n    background-image: linear-gradient(#3c3c3c, #676767) !important;\r\n    text-shadow: none !important;\r\n    background-color: black !important;\r\n}\r\n\r\n/* category bar */\r\n.categoryBar {\r\n\tbackground-color: darkgrey;\r\n}\r\n.categoryBar a {\r\n    color: black !important;\r\n}\r\n.categoryBar .inner a:hover {\r\n    color: #0074be !important;\r\n    background-color: black;\r\n}\r\n.categoryBar a:first-child {\r\n    padding: 0 15px;\r\n}\r\n.categoryBar+.announcementBar {\r\n    background-color: #323a3f;\r\n}\r\n.announcementBar .content .copy span:nth-child(2) {\r\n    color: white !important;\r\n}\r\n\r\n/* header */\r\n.pageHeader h1 {\r\n    color: lightgrey;\r\n}\r\n\r\n/* right side bar */\r\n.sideGridBox {\r\n    background-color: inherit;\r\n}\r\n.sideGridBox h3 {\r\n    background-color: #202020;\r\n}\r\n.sideGridBox h3>a {\r\n    color: lightgrey;\r\n}\r\n\r\n/**/\r\n#fpMainContent .gridHeading .headingRight .button.fpSettingsButton #fpSettingsButton {\r\n    color: lightgrey;\r\n}\r\n#fpMainContent .gridCategory ul.gridDeals .fpGridBox .fpItem .itemImageAndName .itemTitle {\r\n    color: #0074be !important;\r\n}\r\n#mainColumn #fpMainContent .gridCategory:not([data-module-name='Featured Deals']):not(#fpNewsAndArticles) ul.gridDeals .fpGridBox .fpItem .itemImageAndName .itemTitle {\r\n    color: #0074be !important;\r\n}\r\n#fpMainContent .gridCategory ul.gridDeals .fpGridBox .fpItem .itemBottomRow {\r\n    background-color: black !important;\r\n}\r\n#fpMainContent .gridCategory .grid .fpItem .priceLine .itemPrice {\r\n    color: #76b14c !important;\r\n}\r\n#mainColumn #fpMainContent .gridCategory:not([data-module-name='Featured Deals']):not(#fpNewsAndArticles) ul.gridDeals .fpGridBox .itemInfoLine .priceLine .itemPrice {\r\n    color: #76b14c !important;\r\n}\r\n.viewDetailsBtn {\r\n    background-color: #202020;\r\n    color: lightgrey !important;\r\n}\r\n.viewDetailsBtn:hover {\r\n    background-color: #0072bc;\r\n}\r\n.inlineStoreCoupons h2 {\r\n    color: #0074be;\r\n}\r\n.inlineStoreCoupons .postload {\r\n    background-color: inherit;\r\n}\r\n.inlineStoreCoupons .postload .storeName {\r\n    color: lightgrey;\r\n}\r\n.inlineStoreCoupons .postload .couponDesc {\r\n    color: grey;\r\n}\r\n\r\n/******** Category pages ********/\r\n\r\n/* left column */\r\n.leftColumn .box,\r\n#searchSidebarContainer .box {\r\n    background-color: #202020;\r\n}\r\n.sectionTitle {\r\n    color: #0079c7;\r\n}\r\n.box .head {\r\n    color: lightgrey;\r\n}\r\n.shopDeals>ul>li {\r\n    background: transparent;\r\n}\r\n.shopDeals>ul>li a {\r\n    color: lightgrey;\r\n}\r\n.shopDeals ul.subCat {\r\n    background-color: #424242;\r\n}\r\n.facetedNav .section .header .sectionTitle {\r\n    color: lightgrey;\r\n}\r\n.facetedNav .section .scrollable::-webkit-scrollbar {\r\n    background-color: black;\r\n}\r\n.facetedNav .options li .content {\r\n    color: #c3c3c3;\r\n}\r\n.facetedNav .section .options {\r\n    color: lightgrey;\r\n}\r\n.facetedNav input[type=\"text\"] {\r\n    background-color: black;\r\n    color: lightgrey;\r\n}\r\n.shoppingTools .section .title {\r\n    color: lightgrey;\r\n    text-decoration: underline;\r\n}\r\n/******** deals ********/\r\n#fpMainContent .gridHeading>h2,\r\n#fpMainContent .gridHeading>h1\r\n{\r\n    color: #0074be;\r\n}\r\n#fpMainContent .pagination .button {\r\n    color: lightgrey;\r\n}\r\n#fpMainContent .gridCategory .fpGridBox {\r\n    background-color: black;\r\n    border-width: 1px;\r\n}\r\n#fpMainContent .gridCategory .grid .fpItem .itemBottomRow {\r\n    background-color: black;\r\n}\r\n.couponItem .itemBottomRow {\r\n    background-color: inherit;\r\n}\r\n.itemImageAndName:hover {\r\n    background-color: #303030;\r\n}\r\n\r\n/******** coupons and discounts ********/\r\n.couponsDiscounts .box {\r\n    background-color: black;\r\n}\r\n.catModules .moduleTitle {\r\n    color: inherit;\r\n}\r\n.dealGridTitle {\r\n    color: #0074be;\r\n}\r\n.mainContent .box {\r\n    background-color: black;\r\n}\r\n.box p {\r\n    color: lightgrey;\r\n}\r\n.categoryInfo .title {\r\n    color: #0074be;\r\n}\r\n\r\n/******** menu panes ********/\r\n.subPane {\r\n    background-color: #202020 !important;\r\n    color: lightgrey !important;\r\n}\r\n.subContainer, .subContainer .first {\r\n    background-color: #202020;\r\n}\r\n.topHeading .title {\r\n    color: lightgrey;\r\n}\r\n.subContainer>li>a {\r\n    color: lightgrey !important;\r\n    background-color: #202020;\r\n}\r\n.globalNav .deals {\r\n    background-color: #202020;\r\n}\r\n.globalNav ul.subContainer {\r\n    background-color: #202020;\r\n    color: lightgrey !important;\r\n}\r\n.subPaneInfo li a, \r\n.listContainer li a,\r\n.headerArticle .articleTitle a {\r\n    color: lightgrey !important;\r\n}\r\n#globalBar .globalNav li .subContainer p {\r\n    color: grey;\r\n}\r\n\r\n/* modal windows */\r\n.modal {\r\n    background-color: black;\r\n    color: lightgrey;\r\n    border: 1px solid white;\r\n}\r\n.modal .headline {\r\n    color: lightgrey;\r\n}\r\n.modal.modal-modern .dealAlertTitle {\r\n    color: grey;\r\n}\r\n.modal footer {\r\n    background-color: #202020;\r\n}\r\n.modal .close {\r\n    color: white !important;\r\n}\r\n#addDealAlertModal .subtext {\r\n    color: lightgrey;\r\n}\r\n.modal p {\r\n    color: grey;\r\n}\r\n\r\n/* search results */\r\n.resultTabs a.active {\r\n    background-color: #303030;\r\n}\r\n.resultTabs a,\r\n.searchFooter {\r\n    background-color: black;\r\n    color: lightgrey;\r\n}\r\n.dealAlertRow,\r\n.notifBar {\r\n    background-color: #202020;\r\n    color: lightgrey;\r\n}\r\n.dealAlertRow .title {\r\n    color: lightgrey;\r\n}\r\n.notifBar {\r\n    margin: 10px 10px 10px 10px;\r\n}\r\n.mainSearchContent .searchWrapper {\r\n    background-color: black;\r\n}\r\n#afscontainer {\r\n    display: none;\r\n}\r\n.facetedNav .section select {\r\n    color: lightgrey;\r\n    background-image: linear-gradient(#3c3c3c, #676767);\r\n}\r\n.options option {\r\n    background-color: black;\r\n}\r\n}\r\n\r\n@-moz-document url-prefix(\"https://slickdeals.net/f/\") {\r\n/* front page deals */\r\n.frontpageDeal .box,\r\n.popularDeal .box,\r\n.forumThread .box {\r\n    background-color: black;\r\n    color: lightgrey;\r\n}\r\n.frontpageDeal .aboutAuthor {\r\n    color: lightgrey;\r\n}\r\n#weeklyAdBar {\r\n    background-color: inherit;\r\n}\r\n#dealTitle h1,\r\n#dealPrice {\r\n    color: white;\r\n}\r\n#detailsArea {\r\n    color: lightgrey;\r\n}\r\n#detailsTop .textDescription {\r\n    color: lightgrey;\r\n}\r\n.postUsername a {\r\n    color: #0072bc;\r\n}\r\n.postTextContent {\r\n    color: lightgrey;\r\n}\r\n#originalPost, #statisticsAndSubmissions, #joinTheConversationBox, .commentBubble, #dealStats.activeDeal {\r\n    background-color: #3a3a3a;\r\n}\r\n#detailContents .addCommentContainer,\r\n.addCommentContainer {\r\n    background-color: #202020;\r\n}\r\n.quotebox_header {\r\n    color: #adadad;\r\n}\r\n.quotebox_content {\r\n    background-color: #202020;\r\n    color: grey;\r\n}\r\n.authorName>.label>a {\r\n    color: lightgrey;\r\n}\r\n.invertedBadge {\r\n    color: black;\r\n}\r\n#dealStats.activeDeal .getNotified {\r\n    color: lightgrey;\r\n}\r\n.injectedAd {\r\n    background-color: black;\r\n}\r\n.dropdown .dropdown-menu {\r\n    background-color: #202020;\r\n}\r\n.dropdown .dropdown-menu li>a {\r\n    color: lightgrey;\r\n}\r\n}\r\n\r\n@-moz-document url-prefix(\"https://slickdeals.net/coupons\") {\r\ndiv.box {\r\n    background-color: #202020;\r\n    color: lightgrey;\r\n}\r\n.item {\r\n    background-color: black;\r\n}\r\n.item .intro,\r\n.item .title {\r\n    color: lightgrey;\r\n}\r\n.moreDealsBox {\r\n    background-color: black;\r\n    color: grey;\r\n}\r\n.themedBox {\r\n    background-color: #303030;\r\n    \r\n}\r\nh2.title {\r\n    color: lightgrey !important;\r\n}\r\n\r\n/* filters */\r\n.showTabs .filter:not(.active) {\r\n    color: grey;\r\n}\r\n\r\n/* model coupon detail */\r\n#couponModal.modal .inner .couponItemInfo .details .title {\r\n    color: lightgrey;\r\n}\r\n.modal .bottom {\r\n    background-color: #202020;\r\n}\r\n.modal .bottom:not(.modal-modern) .subHead {\r\n    color: grey;\r\n}\r\n#couponModal.modal .bottom form.one input.email {\r\n    background-color: black;\r\n    color: grey;\r\n}\r\n}\r\n\r\n@-moz-document url-prefix(\"https://slickdeals.net/article\") {\r\n.box {\r\n    background-color: #202020;\r\n    border-top: 1px solid grey;\r\n}\r\n.topline {\r\n    border-top: none;\r\n}\r\n#dealTitle h1 {\r\n    color: lightgrey;\r\n}\r\n.subTitle {\r\n    color: #a0a0a0;\r\n}\r\n.author .name {\r\n    color: lightgrey;\r\n}\r\n.badge {\r\n    color: black;\r\n}\r\n.wordpressContent h2 {\r\n    color: grey;\r\n    text-decoration: underline;\r\n}\r\n.wordpressContent ul {\r\n    color: grey;\r\n    background-color: black;\r\n}\r\n.aboutAuthor {\r\n    color: lightgrey !important;\r\n}\r\n.share {\r\n    background-color: #202020;\r\n}\r\n.share .shareArticle {\r\n    color: lightgrey;\r\n}\r\n\r\n/* comments */\r\n.postUsername a,\r\n.articlePage h3,\r\n.postTextContent,\r\n.pageCounter {\r\n    color: lightgrey;\r\n}\r\n\r\n#joinTheConversationBox {\r\n    background-color: #404040;\r\n}\r\n#joinTheConversationBox .joinTheConversation {\r\n    color: lightgrey;\r\n}\r\n}\r\n\r\n@-moz-document url-prefix(\"https://slickdeals.net/forums/\") {\r\n.bodyBg {\r\n    background: none;\r\n}\r\n.loginSignUp .inner {\r\n    background-color: #202020;\r\n}\r\n.loginSignUp .head,\r\n.loginSignUp .subHead {\r\n    color: lightgrey;\r\n}\r\n.modal input.infoField {\r\n    background-color: black;\r\n    color: lightgrey;\r\n}\r\n.modal .bottom {\r\n    background-color: #202020;\r\n    color: grey;\r\n}\r\n.altAccess {\r\n    color: lightgrey;\r\n}\r\n.vbmenu_popup td, .vbmenu_popup li {\r\n    background-color: black;\r\n    color: lightgrey;\r\n}\r\n.vbmenu_option a:link {\r\n    color: lightgrey;\r\n}\r\ntd.vbmenu_hilite {\r\n    background-color: grey;\r\n}\r\n.vbmenu_option .bginput {\r\n    background-color: black;\r\n    color: lightgrey;\r\n}\r\n}\r\n\r\n@-moz-document url-prefix(\"https://slickdeals.net/deal-alerts/\") {\r\n#pageContent .box {\r\n    background-color: #202020;\r\n    color: lightgrey;\r\n}\r\n#dealAlertKeyword, .dealAlertKeywordSearch {\r\n    background-color: black;\r\n    color: lightgrey;\r\n}\r\n.button.alert {\r\n    color: black;\r\n}\r\n}\r\n\r\n@-moz-document url-prefix(\"https://slickdeals.net/forums/forumdisplay.php\") {\r\nbody {\r\n    background: none;\r\n    background-color: black;\r\n}\r\n#logoarea {\r\n    display: none;\r\n}\r\n.global_wrap {\r\n    background-color: #202020;\r\n}\r\n.alt1 {\r\n    background-color: black;\r\n    color: lightgrey;\r\n}\r\n.alt2 {\r\n    background-color: #101010;\r\n    color: lightgrey;\r\n}\r\n.alt2 a {\r\n    color: lightgrey !important;\r\n}\r\n.tlv3_cat .icon,\r\n.navbar h2.forum_navbar_header,\r\n.pagenav_result_text {\r\n    color: lightgrey;\r\n}\r\na:link, a:visited {\r\n    color: #367adc;\r\n}\r\n.forumbutton.blue {\r\n    background-color: #007fa7;\r\n    color: black;\r\n}\r\n.forumbutton {\r\n    background-color: #797900;\r\n    color: black !important;\r\n}\r\n.forumbutton.right {\r\n    background-color: #101010;\r\n    color: lightgrey !important;\r\n}\r\n.forumwrap_top {\r\n    background-color: #101010;\r\n}\r\nh1.forum_threadlist_header, h2.forum_threadlist_header {\r\n    color: grey;\r\n}\r\n.forumwrap_top td.search_pagenav, .search_pagenav {\r\n    background-color: black;\r\n}\r\n.forumwrap>table {\r\n    background-color: black;\r\n}\r\n.forumwrap_bottom_v2 .wrap_table, .forumwrap_bottom .wrap_table {\r\n    background-color: black;\r\n    color: grey;\r\n    margin-top: 0px;\r\n    margin-bottom: 0px;\r\n}\r\n\r\n/* forum options */\r\n.forum_options_header {\r\n    color: lightgrey;\r\n}\r\n.forum_options {\r\n    background-color: #101010;\r\n}\r\n.forum_category_select,\r\n.forum_options_right {\r\n    background-color: black;\r\n}\r\n.forum_options h3,\r\n.forum_legend,\r\n.forum_rules {\r\n    color: grey;\r\n}\r\n.forum_options_right select {\r\n    background-color: black;\r\n    color: grey;\r\n}\r\n/* right side */\r\n.widget_hitbar a, #hottopic_hitbar a {\r\n    color: black;\r\n}\r\n.colitem {\r\n    background-color: #101010;\r\n}\r\n.colitem:hover {\r\n    background-color: #202020;\r\n}\r\n.colitem a, .colitem a:link, .colitem a:visited {\r\n    color: grey;\r\n}\r\n}"}