{
  "id": 179753,
  "name": "Ciemny motyw - mc.skript.pl/wnioski",
  "description": "Ciemny motyw dla mc.skript.pl/wnioski",
  "user": {
    "id": 869849,
    "name": "BrixNW",
    "email": "redacted",
    "paypal_email": null,
    "homepage": null,
    "about": null,
    "license": null
  },
  "updated": "2020-02-01T22:30:28.000Z",
  "weekly_install_count": 0,
  "total_install_count": 4,
  "rating": null,
  "after_screenshot_name": "https://userstyles.org/style_screenshots/179753_after.jpeg?r=1581408086",
  "obsoleting_style_id": null,
  "obsoleting_style_name": null,
  "obsolete": 0,
  "admin_delete_reason_id": null,
  "obsoletion_message": null,
  "screenshots": null,
  "license": "arr",
  "created": "2020-02-01T21:36:41.000Z",
  "category": "site",
  "raw_subcategory": "skript",
  "subcategory": "skript",
  "additional_info": null,
  "style_tags": [],
  "css": "@-moz-document url-prefix(\"https://mc.skript.pl/wnioski\") {\r\nbody {\r\n    background-color: #222;\r\n    background-image: url(https://code.skript.pl/api/background/night);\r\n}\r\n\r\n.card\r\n  {\r\n    background-color: #212121!important;\r\n    color: #fff;\r\n  }\r\n\r\n.sk-item:hover, sk-item-hover {\r\n    color: inherit;\r\n    text-decoration: none;\r\n    background: #3e3e3e;\r\n}\r\n\r\n.sk-item {\r\n    background-color: #212121;\r\n    border-bottom: 1px solid #141414;\r\n}\r\n.sk-neutral {\r\n    color: #bdbdbd;\r\n}\r\n.bg-light{\r\n\tbackground-color: #212121!important;\r\n}\r\n.navbar-light .navbar-nav .nav-link{\r\n    color: #fff !important;\r\n}\r\n\r\n.navbar-brand\r\n{\r\n\tcolor: #fff !important;\r\n}\r\n.dropdown-item {\r\n    color: #fff;\r\n    background-color: #212121;                                          \r\n}\r\n.dropdown-menu{\r\n\tbackground-color: #212121; \r\n}\r\n.dropdown-item:focus, .dropdown-item:hover {\r\n    color: #fff;\r\n    text-decoration: none;\r\n    background-color: #3e3e3e;\r\n}\r\n.form-control{\r\n\tcolor: #fff;\r\n    background-color: #333;\r\n\tborder: 1px solid #141414;\r\n}\r\n.form-control:focus {\r\n    color: #fff;\r\n    background-color: #444;\r\n}\r\n.input-group-text {\r\n    color: #fff;\r\n    background-color: #333;\r\n    border: 1px solid #141414;\r\n}\r\n.sk-label[style='background: #222222; ']{\r\n    background: #5f5f5f!important;\r\n}\r\n\r\n.sk-label[style='background: #222222; opacity: 0.5;']{\r\n\tbackground: #5f5f5f!important;\r\n}\r\n}",
  "discussions": [],
  "discussionsCount": 0,
  "commentsCount": 0,
  "userjs_url": "/styles/userjs/179753/ciemny-motyw-mc-skript-pl-wnioski.user.js",
  "style_settings": []
}