{"id":89234,"name":"Chaos Emeralds Tumblr Home Buttons","category":"site","raw_subcategory":"tumblr","subcategory":"tumblr","style_tags":[],"description":"stylish needs more sonic the hedgehog stuff","user":{"id":193428,"name":"JetSetMedley","email":"redacted","paypal_email":null,"homepage":null,"about":null,"license":null},"admin_delete_reason_id":null,"updated":"2013-12-05T10:53:19.000Z","weekly_install_count":0,"total_install_count":292,"rating":null,"screenshot_url":"https://userstyles.org/auto_style_screenshots/89234-after.png?r=1591517217","url":"/styles/89234/chaos-emeralds-tumblr-home-buttons","discussionsCount":1,"commentsCount":1,"css":"@-moz-document url-prefix('http://www.tumblr.com/'), url-prefix('https://www.tumblr.com/')   {\r\n\r\n\r\n\r\n.new_post_label/*_icon*/ > I {display: none !important}\r\n\r\n.new_post_label {\r\n\r\n  background-clip: content-box;\r\n\r\n  padding: 77px 1px 2px 0 !important;\r\n\r\n}\r\n\r\n.new_post_label:hover {\r\n\r\n  color: black !important;\r\n\r\n  background-color: rgba(192,192,192,.7) !important;\r\n\r\n}\r\n\r\n.new_post_buttons {\r\n\r\n  background: white center no-repeat url('http://i.imgur.com/iEh44Vp.png') !important;\r\n\r\n}\r\n\r\n\r\n\r\n}"}