{
  "id": 95779,
  "name": "Comic Sans MS",
  "description": "Comic Sans MS now for WIKIPEDIA ! Such wow.",
  "user": {
    "id": 250596,
    "name": "Eggburger",
    "email": "redacted",
    "paypal_email": null,
    "homepage": null,
    "about": null,
    "license": null
  },
  "updated": "2013-12-05T01:54:53.000Z",
  "weekly_install_count": 0,
  "total_install_count": 303,
  "rating": null,
  "after_screenshot_name": "https://userstyles.org/style_screenshots/95779_after.png?r=1598429171",
  "obsoleting_style_id": null,
  "obsoleting_style_name": null,
  "obsolete": 0,
  "admin_delete_reason_id": null,
  "obsoletion_message": null,
  "screenshots": [
    "https://userstyles.org/style_screenshots/95779_additional_9519.jpeg?r=1598429171"
  ],
  "license": "publicdomain",
  "created": "2013-12-05T01:54:53.000Z",
  "category": "site",
  "raw_subcategory": "wikipedia",
  "subcategory": "wikipedia",
  "additional_info": "Comic Sans MS now for WIKIPEDIA ! Such wow.",
  "style_tags": [],
  "css": "@namespace url(http://www.w3.org/1999/xhtml);\r\n\r\n@-moz-document domain(\"wikipedia.org\") {\r\n\r\n\r\n    p,a,div,h1,h2,h3{\r\n        font-family:Comic Sans MS;\r\n        font-size:16px;\r\n    }\r\n    \r\n    \r\n}",
  "discussions": [
    {
      "id": 39337,
      "name": "Such WOW indeed",
      "rating": 0,
      "created": "2013-12-06T18:25:35.000Z",
      "author_name": "Eggburger",
      "author_id": 250596
    }
  ],
  "discussionsCount": 1,
  "commentsCount": 2,
  "userjs_url": "/styles/userjs/95779/comic-sans-ms.user.js",
  "style_settings": []
}