{"id":9979,"name":"DarkLyrics.com - White Style (Bright)","category":"site","raw_subcategory":"darklyrics","subcategory":"darklyrics","style_tags":[],"description":"White style for the very black \"Dark Lyrics\" website.  I use DarkLyrics to read-up on all the Metal band's lyrics.  This style makes readability very easy with vista's Calibri font, as well as the wonderful white, and black styling.\r\n\r\n** An original style, made by me, user 7858!\r\n\r\nFeatures:\r\n- Calibri font, although supports XP and Windows 9x with the secondary font being Arial.  (if Calibri is not installed, the site will display in Ariel)\r\n- White background for each page, table data, and paragraph\r\n- WebSafe Orange as Hovered Hyperlink color\r\n- WebSave Red as Visited hyper link color\r\n- Light overall look (was dark, but is no longer!)\r\n\r\nFrom DarkLyrics .com :\r\n\"Metal lyrics. Black death doom heavy power thrash metal hardcore grindcore. Lyrics of metal bands - over 11'000 full albums lyrics.\"\r\n\r\nIntegrates with the following Styles:\r\n+ Style 6657\r\n+ Style 7216\r\n\r\n\r\nFuture Updates:\r\n- I plan to prevent the lyrics themselves from turning Blue and hovering to turn Red.  This will be implemented in a planned update.\r\n\r\nChangelog:\r\n- Initial Release","user":{"id":7858,"name":"dotter","email":"redacted","paypal_email":null,"homepage":null,"about":null,"license":null},"admin_delete_reason_id":null,"updated":"2008-08-25T12:54:35.000Z","weekly_install_count":0,"total_install_count":519,"rating":null,"screenshot_url":"https://userstyles.org/style_screenshots/9979_after.png?r=1591862771","url":"/styles/9979/darklyrics-com-white-style-bright","discussionsCount":0,"commentsCount":0,"css":"/*\r\n _____________________________________________________________________\r\n|                  |                                                  |\r\n|          Title:  |  DarkLyrics.com - White Style (Bright)           |\r\n|    Description:  |  Light Theme and New Fonts (Calibri)             |\r\n|         Author:  |  -=Ben=-                                         |\r\n|   Date Created:  |  August 25, 2008                                 |\r\n|   Last Updated:  |  August 25, 2008                                 |\r\n|        Version:  |  1.0.0.0                                         |\r\n|__________________|__________________________________________________|\r\n\r\n*/\r\n\r\n\r\n\r\n@namespace url(http://www.w3.org/1999/xhtml);\r\n\r\n@-moz-document domain(\"darklyrics.com\") \r\n{\r\n\r\n\r\n\r\n\r\n/*Ben's Hovered HREF Links Color Changing Code:*/\r\na:hover, a:hover > font, a > font:hover, a[href]:hover\r\n{\r\n  color:#FF0000 !important;\r\n}\r\n\r\n/*Ben's Hovered HREF Links Color Changing Code:*/\r\na:visited\r\n{\r\n  color:#ff9933 !important;\r\n}\r\n\r\n/*Ben's Regular HREF Links Color Changing Code:*/\r\na\r\n{\r\n\r\n  color:#0000FF !important;\r\n}\r\n\r\na > font\r\n{\r\n  color: #000000 !important;\r\n}\r\n\r\n\r\nhtml, table, tr, p, body\r\n{\r\n  background-color: #FFFFFF !important;\r\n  color: #000000 !important;\r\n  font-family: Calibri,Arial !important;\r\n  font-size: 12px !important;\r\n  border-color: black !important; \r\n}\r\n\r\ntd,b,p\r\n{\r\n  color: #000000 !important;\r\n}\r\n\r\n\r\nFONT\r\n{\r\n  color: #000000;\r\n  background-color: #FFFFFF !important;\r\n}\r\n\r\nFONT\r\n{\r\n  color: #000000;\r\n  background-color: #FFFFFF;\r\n}\r\n\r\nfont[size=\"4\"][face=\"Helvetica\"][color=\"#ffffcc\"]\r\n{\r\n  color: #000000 !important ;\r\n}\r\n\r\nfont [size=\"5\"][color=\"#ffffcc\"]\r\n{\r\n  color: #000000 !important;\r\n}\r\n\r\n\r\n}"}